setup.py
lenovo/__init__.py
lenovo.egg-info/PKG-INFO
lenovo.egg-info/SOURCES.txt
lenovo.egg-info/dependency_links.txt
lenovo.egg-info/top_level.txt